Metadata-Version: 2.1
Name: trans-fpdf
Version: 0.1.4
Summary: Trans FPDF for Python
Home-page: https://github.com/miklagard/transpdf.git
Author: Cem Yildiz
Author-email: cem.yildiz@yandex.com.tr
Classifier: Programming Language :: Python :: 3
Classifier: License :: OSI Approved :: MIT License
Classifier: Operating System :: OS Independent
Requires-Python: >=3.6
License-File: LICENCE
